y360_orglib/__init__.py
y360_orglib/audit/__init__.py
y360_orglib/audit/audit_events.py
y360_orglib/audit/audit_mail.py
y360_orglib/audit/event_models.py
y360_orglib/audit/models.py
y360_orglib/common/__init__.py
y360_orglib/common/exceptions.py
y360_orglib/common/http.py
y360_orglib/directory/__init__.py
y360_orglib/directory/directory_client.py
y360_orglib/directory/models.py
y360_orglib/disk/__init__.py
y360_orglib/disk/disk_admin.py
y360_orglib/disk/disk_client.py
y360_orglib/disk/models.py
y360_orglib/logging/__init__.py
y360_orglib/logging/config.py
y360_orglib/service_app/__init__.py
y360_orglib/service_app/models.py
y360_orglib/service_app/service_client.py
y360_orglib-0.0.13.dist-info/METADATA
y360_orglib-0.0.13.dist-info/WHEEL
y360_orglib-0.0.13.dist-info/top_level.txt
y360_orglib-0.0.13.dist-info/RECORD
